<?xml version="1.0" encoding="utf-8"?>
<ArrayOfArrayOfVariableData xmlns:xsd="http://www.w3.org/2001/XMLSchema" xmlns:xsi="http://www.w3.org/2001/XMLSchema-instance">
  <ArrayOfVariableData>
    <VariableData>
      <Name>TestRunDate</Name>
      <Values>
        <Value>26.03.2024 10:31:04</Value>
      </Values>
    </VariableData>
    <VariableData>
      <Name>Probenname</Name>
      <Values>
        <Value>20240227_7188_M03_Z6_E</Value>
      </Values>
    </VariableData>
    <VariableData>
      <Name>TestName</Name>
      <Values>
        <Value>E_Modul_Beton_Zylinder 2</Value>
      </Values>
    </VariableData>
    <VariableData>
      <Name>TestRunName</Name>
      <Values>
        <Value>Test Run 15</Value>
      </Values>
    </VariableData>
    <VariableData>
      <Name>Druckfestigkeit</Name>
      <Values>
        <Value>43.89</Value>
      </Values>
      <Unit>N/mm²</Unit>
    </VariableData>
    <VariableData>
      <Name>E_Modul</Name>
      <Values>
        <Value>-34130.8777130926</Value>
      </Values>
      <Unit>N/mm²</Unit>
    </VariableData>
    <VariableData>
      <Name>Durchmesser</Name>
      <Values>
        <Value>99</Value>
      </Values>
      <Unit>mm</Unit>
    </VariableData>
    <VariableData>
      <Name>Länge</Name>
      <Values>
        <Value>299.9</Value>
      </Values>
      <Unit>mm</Unit>
    </VariableData>
    <VariableData>
      <Name>Masse</Name>
      <Values>
        <Value>5.426</Value>
      </Values>
      <Unit>kg</Unit>
    </VariableData>
    <VariableData>
      <Name>Grundfläche</Name>
      <Values>
        <Value>7697.68739945839</Value>
      </Values>
      <Unit>mm²</Unit>
    </VariableData>
    <VariableData>
      <Name>Rohdichte</Name>
      <Values>
        <Value>0.002350406898457</Value>
      </Values>
      <Unit>g/mm³</Unit>
    </VariableData>
    <VariableData>
      <Name>Messlänge</Name>
      <Values>
        <Value>100</Value>
      </Values>
      <Unit>mm</Unit>
    </VariableData>
    <VariableData>
      <Name>Dehnung</Name>
      <Values>
        <Value>-0.000300219556569</Value>
      </Values>
      <Unit>mm/mm</Unit>
    </VariableData>
    <VariableData>
      <Name>Ch1_obere_Prüfkraft</Name>
      <Values>
        <Value>-112636.1171875</Value>
      </Values>
      <Unit>N</Unit>
    </VariableData>
    <VariableData>
      <Name>Ch1_untere_Prüfkraft</Name>
      <Values>
        <Value>-33759.78515625</Value>
      </Values>
      <Unit>N</Unit>
    </VariableData>
    <VariableData>
      <Name>ClipOn_1470533_Abweichung_1</Name>
      <Values>
        <Value>9.26550110997796</Value>
      </Values>
      <Unit>%</Unit>
    </VariableData>
    <VariableData>
      <Name>ClipOn_1470534_Abweichung_1</Name>
      <Values>
        <Value>15.0560307369408</Value>
      </Values>
      <Unit>%</Unit>
    </VariableData>
    <VariableData>
      <Name>ClipOn_1470535_Abweichung_1</Name>
      <Values>
        <Value>16.8473117643932</Value>
      </Values>
      <Unit>%</Unit>
    </VariableData>
    <VariableData>
      <Name>ClipOn_1470533_Abweichung_2</Name>
      <Values>
        <Value>-4.03667009508616</Value>
      </Values>
      <Unit>%</Unit>
    </VariableData>
    <VariableData>
      <Name>ClipOn_1470534_Abweichung_2</Name>
      <Values>
        <Value>3.00683534890416</Value>
      </Values>
      <Unit>%</Unit>
    </VariableData>
    <VariableData>
      <Name>ClipOn_1470535_Abweichung_2</Name>
      <Values>
        <Value>4.08132400963156</Value>
      </Values>
      <Unit>%</Unit>
    </VariableData>
    <VariableData>
      <Name>Prüfer</Name>
      <Values>
        <Value>Be</Value>
      </Values>
    </VariableData>
  </ArrayOfVariableData>
</ArrayOfArrayOfVariableData>